acmens.py
acmens-0.3.0.dist-info/LICENSE
acmens-0.3.0.dist-info/METADATA
acmens-0.3.0.dist-info/WHEEL
acmens-0.3.0.dist-info/entry_points.txt
acmens-0.3.0.dist-info/top_level.txt
acmens-0.3.0.dist-info/RECORD
