Metadata-Version: 2.1
Name: acmens
Version: 0.3.0
Summary: An ACMEv2 client. Fork of acme-nosudo.
Home-page: https://github.com/r5d/acmens
Author: siddharth ravikumar
Author-email: s@ricketyspace.net
License: GNU Affero General Public License v3
Keywords: acme letsencrypt acmens
Platform: UNKNOWN
Classifier: Development Status :: 2 - Pre-Alpha
Classifier: Environment :: Console
Classifier: Intended Audience :: Developers
Classifier: Intended Audience :: End Users/Desktop
Classifier: License :: OSI Approved :: GNU Affero General Public License v3
Classifier: Operating System :: POSIX :: BSD
Classifier: Operating System :: POSIX :: Linux
Classifier: Operating System :: MacOS
Classifier: Programming Language :: Python :: 3 :: Only
Classifier: Topic :: System :: Systems Administration
Classifier: Topic :: Utilities
Requires-Python: >=3
License-File: LICENSE
